img_preprocessing/__init__.py
img_preprocessing/img_fn.py
img_preprocessing-0.3.dist-info/METADATA
img_preprocessing-0.3.dist-info/WHEEL
img_preprocessing-0.3.dist-info/top_level.txt
img_preprocessing-0.3.dist-info/RECORD
