Metadata-Version: 2.1
Name: img-preprocessing
Version: 0.3
Summary: Image Preprocessing
Home-page: UNKNOWN
Author: hyebin
Author-email: heybin2125@epozen.com
License: UNKNOWN
Keywords: pypi deploy
Platform: UNKNOWN
Classifier: Programming Language :: Python :: 3
Classifier: Programming Language :: Python :: 3.2
Classifier: Programming Language :: Python :: 3.3
Classifier: Programming Language :: Python :: 3.4
Classifier: Programming Language :: Python :: 3.5
Classifier: Programming Language :: Python :: 3.6
Classifier: Programming Language :: Python :: 3.7
Requires-Python: >=3
